{"stats": {"defaultLane": "bottom", "cid": 360, "lane": "bottom", "vsLane": "jungle", "analysed": 19058075, "avgWr": 52.04, "br": 3.57, "pr": "3.68", "wr": "53.03", "lanes": {"top": 0.6, "jungle": 0, "middle": 0.8, "bottom": 98.6, "support": 0.1}, "counters": {"strong": [82, 950, 104], "weak": [25, 68, 30]}}, "counters": [{"cid": 82, "vsWr": 57.66, "n": 111, "d1": 8.66, "d2": 3.59, "allWr": 49, "defaultLane": "top"}, {"cid": 950, "vsWr": 57.38, "n": 840, "d1": 8.53, "d2": 3.46, "allWr": 48.85, "defaultLane": "middle"}, {"cid": 104, "vsWr": 56.55, "n": 1473, "d1": 8.05, "d2": 2.98, "allWr": 48.5, "defaultLane": "jungle"}, {"cid": 102, "vsWr": 56.42, "n": 296, "d1": 6.04, "d2": 0.97, "allWr": 50.38, "defaultLane": "jungle"}, {"cid": 36, "vsWr": 55.95, "n": 1101, "d1": 7.41, "d2": 2.34, "allWr": 48.54, "defaultLane": "top"}, {"cid": 91, "vsWr": 55.59, "n": 1725, "d1": 7.42, "d2": 2.35, "allWr": 48.17, "defaultLane": "jungle"}, {"cid": 32, "vsWr": 55.52, "n": 661, "d1": 7.58, "d2": 2.51, "allWr": 47.94, "defaultLane": "jungle"}, {"cid": 246, "vsWr": 55.38, "n": 1217, "d1": 5.64, "d2": 0.57, "allWr": 49.74, "defaultLane": "jungle"}, {"cid": 24, "vsWr": 55.23, "n": 822, "d1": 7.24, "d2": 2.17, "allWr": 47.99, "defaultLane": "top"}, {"cid": 203, "vsWr": 55.19, "n": 732, "d1": 8.48, "d2": 3.41, "allWr": 46.71, "defaultLane": "jungle"}, {"cid": 31, "vsWr": 55.17, "n": 174, "d1": 8.71, "d2": 3.64, "allWr": 46.46, "defaultLane": "top"}, {"cid": 234, "vsWr": 55.01, "n": 4994, "d1": 5.22, "d2": 0.15, "allWr": 49.79, "defaultLane": "jungle"}, {"cid": 238, "vsWr": 54.93, "n": 2223, "d1": 7.32, "d2": 2.25, "allWr": 47.61, "defaultLane": "middle"}, {"cid": 107, "vsWr": 54.75, "n": 1810, "d1": 7.76, "d2": 2.69, "allWr": 46.99, "defaultLane": "jungle"}, {"cid": 79, "vsWr": 54.72, "n": 254, "d1": 7.39, "d2": 2.32, "allWr": 47.33, "defaultLane": "top"}, {"cid": 54, "vsWr": 54.66, "n": 1158, "d1": 4.48, "d2": -0.59, "allWr": 50.18, "defaultLane": "top"}, {"cid": 876, "vsWr": 54.63, "n": 950, "d1": 7.44, "d2": 2.37, "allWr": 47.19, "defaultLane": "jungle"}, {"cid": 56, "vsWr": 54.57, "n": 909, "d1": 6.33, "d2": 1.26, "allWr": 48.24, "defaultLane": "jungle"}, {"cid": 78, "vsWr": 54.55, "n": 176, "d1": 5.69, "d2": 0.62, "allWr": 48.86, "defaultLane": "support"}, {"cid": 60, "vsWr": 54.55, "n": 924, "d1": 7.41, "d2": 2.34, "allWr": 47.14, "defaultLane": "jungle"}, {"cid": 33, "vsWr": 54.51, "n": 510, "d1": 8.56, "d2": 3.5, "allWr": 45.95, "defaultLane": "jungle"}, {"cid": 113, "vsWr": 54.49, "n": 468, "d1": 5.86, "d2": 0.79, "allWr": 48.63, "defaultLane": "jungle"}, {"cid": 254, "vsWr": 53.91, "n": 985, "d1": 4.37, "d2": -0.7, "allWr": 49.54, "defaultLane": "jungle"}, {"cid": 131, "vsWr": 53.89, "n": 4105, "d1": 7.18, "d2": 2.11, "allWr": 46.71, "defaultLane": "jungle"}, {"cid": 517, "vsWr": 53.68, "n": 1630, "d1": 5.13, "d2": 0.06, "allWr": 48.55, "defaultLane": "middle"}, {"cid": 35, "vsWr": 53.66, "n": 1284, "d1": 7.48, "d2": 2.41, "allWr": 46.18, "defaultLane": "jungle"}, {"cid": 233, "vsWr": 53.66, "n": 969, "d1": 5.69, "d2": 0.62, "allWr": 47.97, "defaultLane": "jungle"}, {"cid": 121, "vsWr": 53.58, "n": 3225, "d1": 6.95, "d2": 1.88, "allWr": 46.63, "defaultLane": "jungle"}, {"cid": 799, "vsWr": 53.14, "n": 1018, "d1": 2.18, "d2": -2.89, "allWr": 50.96, "defaultLane": "top"}, {"cid": 200, "vsWr": 52.89, "n": 641, "d1": 6.41, "d2": 1.34, "allWr": 46.48, "defaultLane": "jungle"}, {"cid": 59, "vsWr": 52.78, "n": 2374, "d1": 4.49, "d2": -0.58, "allWr": 48.29, "defaultLane": "jungle"}, {"cid": 11, "vsWr": 52.77, "n": 1516, "d1": 5.59, "d2": 0.52, "allWr": 47.18, "defaultLane": "jungle"}, {"cid": 126, "vsWr": 52.68, "n": 2559, "d1": 2.84, "d2": -2.23, "allWr": 49.84, "defaultLane": "jungle"}, {"cid": 80, "vsWr": 52.65, "n": 226, "d1": 4.25, "d2": -0.82, "allWr": 48.4, "defaultLane": "support"}, {"cid": 64, "vsWr": 52.56, "n": 3343, "d1": 4.95, "d2": -0.12, "allWr": 47.61, "defaultLane": "jungle"}, {"cid": 141, "vsWr": 52.34, "n": 1450, "d1": 3.76, "d2": -1.31, "allWr": 48.58, "defaultLane": "jungle"}, {"cid": 887, "vsWr": 52.16, "n": 1599, "d1": 6.14, "d2": 1.07, "allWr": 46.02, "defaultLane": "jungle"}, {"cid": 72, "vsWr": 51.87, "n": 214, "d1": 3.97, "d2": -1.1, "allWr": 47.9, "defaultLane": "jungle"}, {"cid": 106, "vsWr": 51.75, "n": 1747, "d1": 5.72, "d2": 0.65, "allWr": 46.03, "defaultLane": "jungle"}, {"cid": 76, "vsWr": 51.68, "n": 776, "d1": 4.52, "d2": -0.55, "allWr": 47.16, "defaultLane": "jungle"}, {"cid": 48, "vsWr": 51.56, "n": 256, "d1": 3.72, "d2": -1.35, "allWr": 47.84, "defaultLane": "top"}, {"cid": 62, "vsWr": 51.26, "n": 1030, "d1": 2.7, "d2": -2.37, "allWr": 48.56, "defaultLane": "jungle"}, {"cid": 77, "vsWr": 51.14, "n": 569, "d1": 4, "d2": -1.07, "allWr": 47.14, "defaultLane": "jungle"}, {"cid": 245, "vsWr": 51.13, "n": 3450, "d1": 4.1, "d2": -0.97, "allWr": 47.03, "defaultLane": "jungle"}, {"cid": 120, "vsWr": 51.02, "n": 1562, "d1": 2.14, "d2": -2.93, "allWr": 48.88, "defaultLane": "jungle"}, {"cid": 75, "vsWr": 50.82, "n": 122, "d1": 4.14, "d2": -0.93, "allWr": 46.68, "defaultLane": "top"}, {"cid": 163, "vsWr": 50.34, "n": 594, "d1": 2, "d2": -3.07, "allWr": 48.34, "defaultLane": "middle"}, {"cid": 19, "vsWr": 50.28, "n": 543, "d1": 3.02, "d2": -2.05, "allWr": 47.26, "defaultLane": "jungle"}, {"cid": 20, "vsWr": 50.11, "n": 1355, "d1": 4.19, "d2": -0.87, "allWr": 45.92, "defaultLane": "jungle"}, {"cid": 266, "vsWr": 50.09, "n": 543, "d1": 1.11, "d2": -3.96, "allWr": 48.98, "defaultLane": "top"}, {"cid": 5, "vsWr": 50.05, "n": 1033, "d1": 1.67, "d2": -3.4, "allWr": 48.38, "defaultLane": "jungle"}, {"cid": 421, "vsWr": 49.95, "n": 1059, "d1": 4.87, "d2": -0.19, "allWr": 45.08, "defaultLane": "jungle"}, {"cid": 28, "vsWr": 49.42, "n": 945, "d1": 3.06, "d2": -2.01, "allWr": 46.36, "defaultLane": "jungle"}, {"cid": 143, "vsWr": 49.25, "n": 333, "d1": 3.18, "d2": -1.89, "allWr": 46.07, "defaultLane": "support"}, {"cid": 154, "vsWr": 49.16, "n": 1312, "d1": 3.05, "d2": -2.02, "allWr": 46.11, "defaultLane": "jungle"}, {"cid": 904, "vsWr": 49.03, "n": 518, "d1": 0.62, "d2": -4.45, "allWr": 48.41, "defaultLane": "top"}, {"cid": 9, "vsWr": 47.41, "n": 810, "d1": 1.82, "d2": -3.24, "allWr": 45.59, "defaultLane": "jungle"}, {"cid": 427, "vsWr": 47.25, "n": 618, "d1": 1.51, "d2": -3.55, "allWr": 45.74, "defaultLane": "jungle"}, {"cid": 30, "vsWr": 46.78, "n": 699, "d1": -1.12, "d2": -6.19, "allWr": 47.9, "defaultLane": "jungle"}, {"cid": 68, "vsWr": 45.19, "n": 104, "d1": 0.19, "d2": -4.87, "allWr": 45, "defaultLane": "top"}, {"cid": 25, "vsWr": 44.86, "n": 107, "d1": -1.05, "d2": -6.11, "allWr": 45.91, "defaultLane": "support"}], "response": {"valid": true, "duration": "17"}}