{"stats": {"defaultLane": "top", "cid": 516, "lane": "top", "vsLane": "bottom", "analysed": 19058075, "avgWr": 52.04, "br": 0.46, "pr": "4.64", "wr": "53.07", "lanes": {"top": 96.8, "jungle": 0.5, "middle": 1.8, "bottom": 0.1, "support": 0.8}, "counters": {"strong": [81, 800, 21], "weak": [134, 157, 895]}}, "counters": [{"cid": 81, "vsWr": 56.21, "n": 5465, "d1": 5.22, "d2": 0.11, "allWr": 50.99, "defaultLane": "bottom"}, {"cid": 800, "vsWr": 55.62, "n": 338, "d1": 5.48, "d2": 0.37, "allWr": 50.14, "defaultLane": "middle"}, {"cid": 21, "vsWr": 55.17, "n": 2817, "d1": 8.27, "d2": 3.16, "allWr": 46.9, "defaultLane": "bottom"}, {"cid": 804, "vsWr": 54.99, "n": 4632, "d1": 4.9, "d2": -0.21, "allWr": 50.09, "defaultLane": "bottom"}, {"cid": 119, "vsWr": 54.98, "n": 1968, "d1": 6.98, "d2": 1.87, "allWr": 48, "defaultLane": "bottom"}, {"cid": 145, "vsWr": 54.62, "n": 7386, "d1": 5.59, "d2": 0.48, "allWr": 49.03, "defaultLane": "bottom"}, {"cid": 202, "vsWr": 54.1, "n": 5026, "d1": 5.74, "d2": 0.63, "allWr": 48.36, "defaultLane": "bottom"}, {"cid": 498, "vsWr": 54.07, "n": 1215, "d1": 6.5, "d2": 1.39, "allWr": 47.57, "defaultLane": "bottom"}, {"cid": 51, "vsWr": 54, "n": 6929, "d1": 6.08, "d2": 0.97, "allWr": 47.92, "defaultLane": "bottom"}, {"cid": 523, "vsWr": 53.83, "n": 5985, "d1": 5.37, "d2": 0.26, "allWr": 48.46, "defaultLane": "bottom"}, {"cid": 67, "vsWr": 53.79, "n": 2573, "d1": 6.15, "d2": 1.04, "allWr": 47.64, "defaultLane": "bottom"}, {"cid": 235, "vsWr": 53.61, "n": 194, "d1": 6.22, "d2": 1.11, "allWr": 47.39, "defaultLane": "support"}, {"cid": 236, "vsWr": 53.37, "n": 4971, "d1": 5.03, "d2": -0.08, "allWr": 48.34, "defaultLane": "bottom"}, {"cid": 22, "vsWr": 52.74, "n": 2171, "d1": 5.89, "d2": 0.78, "allWr": 46.85, "defaultLane": "bottom"}, {"cid": 221, "vsWr": 52.64, "n": 1252, "d1": 3.87, "d2": -1.24, "allWr": 48.77, "defaultLane": "bottom"}, {"cid": 910, "vsWr": 52.45, "n": 204, "d1": 5.19, "d2": 0.08, "allWr": 47.26, "defaultLane": "middle"}, {"cid": 222, "vsWr": 52.42, "n": 6091, "d1": 6.93, "d2": 1.83, "allWr": 45.49, "defaultLane": "bottom"}, {"cid": 429, "vsWr": 52.23, "n": 381, "d1": 2.54, "d2": -2.57, "allWr": 49.69, "defaultLane": "bottom"}, {"cid": 42, "vsWr": 52.18, "n": 2476, "d1": 3.49, "d2": -1.62, "allWr": 48.69, "defaultLane": "bottom"}, {"cid": 96, "vsWr": 52.04, "n": 736, "d1": 6.57, "d2": 1.47, "allWr": 45.47, "defaultLane": "bottom"}, {"cid": 901, "vsWr": 51.71, "n": 3804, "d1": 4.1, "d2": -1.01, "allWr": 47.61, "defaultLane": "bottom"}, {"cid": 29, "vsWr": 51.55, "n": 2838, "d1": 5.07, "d2": -0.04, "allWr": 46.48, "defaultLane": "bottom"}, {"cid": 69, "vsWr": 51.45, "n": 138, "d1": 5.2, "d2": 0.09, "allWr": 46.25, "defaultLane": "middle"}, {"cid": 110, "vsWr": 51.39, "n": 2732, "d1": 2.72, "d2": -2.39, "allWr": 48.67, "defaultLane": "bottom"}, {"cid": 136, "vsWr": 51.07, "n": 280, "d1": 5.06, "d2": -0.05, "allWr": 46.01, "defaultLane": "middle"}, {"cid": 18, "vsWr": 50.99, "n": 1961, "d1": 3.92, "d2": -1.19, "allWr": 47.07, "defaultLane": "bottom"}, {"cid": 30, "vsWr": 50.83, "n": 242, "d1": 5.45, "d2": 0.35, "allWr": 45.38, "defaultLane": "jungle"}, {"cid": 15, "vsWr": 50.75, "n": 3945, "d1": 4.16, "d2": -0.95, "allWr": 46.59, "defaultLane": "bottom"}, {"cid": 50, "vsWr": 50.48, "n": 727, "d1": 6.05, "d2": 0.96, "allWr": 44.43, "defaultLane": "bottom"}, {"cid": 360, "vsWr": 50.1, "n": 1431, "d1": 3.13, "d2": -1.98, "allWr": 46.97, "defaultLane": "bottom"}, {"cid": 99, "vsWr": 50, "n": 444, "d1": 3.77, "d2": -1.34, "allWr": 46.23, "defaultLane": "middle"}, {"cid": 101, "vsWr": 50, "n": 120, "d1": 3.87, "d2": -1.24, "allWr": 46.13, "defaultLane": "middle"}, {"cid": 147, "vsWr": 49.68, "n": 469, "d1": 3.09, "d2": -2.02, "allWr": 46.59, "defaultLane": "support"}, {"cid": 45, "vsWr": 49.32, "n": 440, "d1": 4.96, "d2": -0.13, "allWr": 44.36, "defaultLane": "middle"}, {"cid": 63, "vsWr": 49.14, "n": 291, "d1": 5.04, "d2": -0.05, "allWr": 44.1, "defaultLane": "support"}, {"cid": 161, "vsWr": 48.75, "n": 279, "d1": 2.98, "d2": -2.12, "allWr": 45.77, "defaultLane": "support"}, {"cid": 8, "vsWr": 48.37, "n": 153, "d1": 0.1, "d2": -5.01, "allWr": 48.27, "defaultLane": "middle"}, {"cid": 115, "vsWr": 47.56, "n": 818, "d1": 1.27, "d2": -3.84, "allWr": 46.29, "defaultLane": "bottom"}, {"cid": 112, "vsWr": 47.37, "n": 114, "d1": 2, "d2": -3.1, "allWr": 45.37, "defaultLane": "middle"}, {"cid": 895, "vsWr": 47.11, "n": 953, "d1": 2.61, "d2": -2.48, "allWr": 44.5, "defaultLane": "bottom"}, {"cid": 157, "vsWr": 47.05, "n": 440, "d1": 2.18, "d2": -2.92, "allWr": 44.87, "defaultLane": "middle"}, {"cid": 134, "vsWr": 45.5, "n": 189, "d1": 0.02, "d2": -5.08, "allWr": 45.48, "defaultLane": "middle"}], "response": {"valid": true, "duration": "46"}}