{"stats": {"defaultLane": "jungle", "cid": 30, "lane": "bottom", "vsLane": "top", "analysed": 19058075, "avgWr": 52.04, "br": 2.42, "pr": "0.54", "wr": "54.62", "lanes": {"top": 2.4, "jungle": 72.2, "middle": 5.4, "bottom": 19.3, "support": 0.7}, "counters": {"strong": [157, 23, 777], "weak": [58, 114, 126]}}, "counters": [{"cid": 157, "vsWr": 62.71, "n": 177, "d1": 14.08, "d2": 7.41, "allWr": 48.63, "defaultLane": "middle"}, {"cid": 23, "vsWr": 62.04, "n": 108, "d1": 12.97, "d2": 6.3, "allWr": 49.07, "defaultLane": "top"}, {"cid": 777, "vsWr": 61.59, "n": 151, "d1": 12.1, "d2": 5.44, "allWr": 49.49, "defaultLane": "middle"}, {"cid": 24, "vsWr": 60.23, "n": 347, "d1": 12.21, "d2": 5.54, "allWr": 48.02, "defaultLane": "top"}, {"cid": 799, "vsWr": 60, "n": 330, "d1": 10.65, "d2": 3.99, "allWr": 49.35, "defaultLane": "top"}, {"cid": 875, "vsWr": 59.62, "n": 208, "d1": 11.62, "d2": 4.95, "allWr": 48, "defaultLane": "top"}, {"cid": 240, "vsWr": 59.13, "n": 115, "d1": 12.25, "d2": 5.58, "allWr": 46.88, "defaultLane": "top"}, {"cid": 6, "vsWr": 59.12, "n": 181, "d1": 12.27, "d2": 5.6, "allWr": 46.85, "defaultLane": "top"}, {"cid": 897, "vsWr": 58.94, "n": 246, "d1": 7.99, "d2": 1.34, "allWr": 50.95, "defaultLane": "top"}, {"cid": 85, "vsWr": 58.71, "n": 155, "d1": 12.5, "d2": 5.83, "allWr": 46.21, "defaultLane": "top"}, {"cid": 68, "vsWr": 58.47, "n": 183, "d1": 10.51, "d2": 3.84, "allWr": 47.96, "defaultLane": "top"}, {"cid": 82, "vsWr": 57.49, "n": 167, "d1": 8.72, "d2": 2.05, "allWr": 48.77, "defaultLane": "top"}, {"cid": 266, "vsWr": 57.46, "n": 315, "d1": 8.71, "d2": 2.04, "allWr": 48.75, "defaultLane": "top"}, {"cid": 13, "vsWr": 57.43, "n": 101, "d1": 8.67, "d2": 2, "allWr": 48.76, "defaultLane": "middle"}, {"cid": 122, "vsWr": 57.14, "n": 301, "d1": 8.89, "d2": 2.22, "allWr": 48.25, "defaultLane": "top"}, {"cid": 31, "vsWr": 56.93, "n": 137, "d1": 8.6, "d2": 1.93, "allWr": 48.33, "defaultLane": "top"}, {"cid": 79, "vsWr": 56.49, "n": 131, "d1": 7.99, "d2": 1.32, "allWr": 48.5, "defaultLane": "top"}, {"cid": 10, "vsWr": 56.41, "n": 195, "d1": 10.77, "d2": 4.11, "allWr": 45.64, "defaultLane": "top"}, {"cid": 75, "vsWr": 56.34, "n": 142, "d1": 9.52, "d2": 2.85, "allWr": 46.82, "defaultLane": "top"}, {"cid": 83, "vsWr": 55.86, "n": 111, "d1": 6.49, "d2": -0.17, "allWr": 49.37, "defaultLane": "top"}, {"cid": 27, "vsWr": 55.63, "n": 151, "d1": 10.02, "d2": 3.36, "allWr": 45.61, "defaultLane": "top"}, {"cid": 84, "vsWr": 55.22, "n": 134, "d1": 6.79, "d2": 0.12, "allWr": 48.43, "defaultLane": "middle"}, {"cid": 54, "vsWr": 54.95, "n": 313, "d1": 7.29, "d2": 0.62, "allWr": 47.66, "defaultLane": "top"}, {"cid": 39, "vsWr": 54.47, "n": 235, "d1": 6.96, "d2": 0.29, "allWr": 47.51, "defaultLane": "top"}, {"cid": 110, "vsWr": 53.69, "n": 203, "d1": 7.2, "d2": 0.53, "allWr": 46.49, "defaultLane": "bottom"}, {"cid": 106, "vsWr": 53.33, "n": 150, "d1": 5.01, "d2": -1.66, "allWr": 48.32, "defaultLane": "jungle"}, {"cid": 86, "vsWr": 53.27, "n": 199, "d1": 4.52, "d2": -2.15, "allWr": 48.75, "defaultLane": "top"}, {"cid": 36, "vsWr": 53.02, "n": 215, "d1": 4.4, "d2": -2.27, "allWr": 48.62, "defaultLane": "top"}, {"cid": 150, "vsWr": 52.85, "n": 193, "d1": 4.61, "d2": -2.06, "allWr": 48.24, "defaultLane": "top"}, {"cid": 98, "vsWr": 52.77, "n": 235, "d1": 6.1, "d2": -0.57, "allWr": 46.67, "defaultLane": "top"}, {"cid": 67, "vsWr": 52.66, "n": 169, "d1": 4.49, "d2": -2.18, "allWr": 48.17, "defaultLane": "bottom"}, {"cid": 887, "vsWr": 52.42, "n": 227, "d1": 6.31, "d2": -0.36, "allWr": 46.11, "defaultLane": "jungle"}, {"cid": 92, "vsWr": 52.35, "n": 298, "d1": 6.57, "d2": -0.09, "allWr": 45.78, "defaultLane": "top"}, {"cid": 516, "vsWr": 52.19, "n": 251, "d1": 5.26, "d2": -1.41, "allWr": 46.93, "defaultLane": "top"}, {"cid": 2, "vsWr": 52.1, "n": 119, "d1": 5.32, "d2": -1.35, "allWr": 46.78, "defaultLane": "top"}, {"cid": 41, "vsWr": 50.53, "n": 285, "d1": 3.42, "d2": -3.25, "allWr": 47.11, "defaultLane": "top"}, {"cid": 904, "vsWr": 50.45, "n": 337, "d1": 2.92, "d2": -3.75, "allWr": 47.53, "defaultLane": "top"}, {"cid": 14, "vsWr": 50, "n": 228, "d1": 1.45, "d2": -5.22, "allWr": 48.55, "defaultLane": "top"}, {"cid": 164, "vsWr": 50, "n": 168, "d1": 2.16, "d2": -4.51, "allWr": 47.84, "defaultLane": "top"}, {"cid": 8, "vsWr": 49.3, "n": 142, "d1": 0.53, "d2": -6.14, "allWr": 48.77, "defaultLane": "middle"}, {"cid": 126, "vsWr": 47.02, "n": 168, "d1": -1.85, "d2": -8.52, "allWr": 48.87, "defaultLane": "jungle"}, {"cid": 114, "vsWr": 46.25, "n": 240, "d1": -1.14, "d2": -7.81, "allWr": 47.39, "defaultLane": "top"}, {"cid": 58, "vsWr": 44.94, "n": 336, "d1": -3.73, "d2": -10.4, "allWr": 48.67, "defaultLane": "top"}], "response": {"valid": true, "duration": "24"}}