{"stats": {"defaultLane": "top", "cid": 799, "lane": "top", "vsLane": "jungle", "analysed": 19058075, "avgWr": 52.04, "br": 9.76, "pr": "6.08", "wr": "50.65", "lanes": {"top": 60.9, "jungle": 34.9, "middle": 4.2, "bottom": 0, "support": 0.1}, "counters": {"strong": [75, 2, 48], "weak": [31, 78, 9]}}, "counters": [{"cid": 75, "vsWr": 62.42, "n": 149, "d1": 15.74, "d2": 13.05, "allWr": 46.68, "defaultLane": "top"}, {"cid": 2, "vsWr": 58, "n": 100, "d1": 9.08, "d2": 6.39, "allWr": 48.92, "defaultLane": "top"}, {"cid": 48, "vsWr": 56.75, "n": 289, "d1": 8.91, "d2": 6.22, "allWr": 47.84, "defaultLane": "top"}, {"cid": 102, "vsWr": 56.71, "n": 328, "d1": 6.33, "d2": 3.64, "allWr": 50.38, "defaultLane": "jungle"}, {"cid": 54, "vsWr": 55.92, "n": 1783, "d1": 5.74, "d2": 3.05, "allWr": 50.18, "defaultLane": "top"}, {"cid": 63, "vsWr": 55.81, "n": 172, "d1": 8.57, "d2": 5.88, "allWr": 47.24, "defaultLane": "support"}, {"cid": 19, "vsWr": 54.22, "n": 509, "d1": 6.96, "d2": 4.27, "allWr": 47.26, "defaultLane": "jungle"}, {"cid": 77, "vsWr": 53.65, "n": 822, "d1": 6.51, "d2": 3.82, "allWr": 47.14, "defaultLane": "jungle"}, {"cid": 32, "vsWr": 53.6, "n": 584, "d1": 5.66, "d2": 2.97, "allWr": 47.94, "defaultLane": "jungle"}, {"cid": 82, "vsWr": 53.1, "n": 145, "d1": 4.1, "d2": 1.41, "allWr": 49, "defaultLane": "top"}, {"cid": 33, "vsWr": 52.82, "n": 657, "d1": 6.87, "d2": 4.18, "allWr": 45.95, "defaultLane": "jungle"}, {"cid": 68, "vsWr": 52.82, "n": 142, "d1": 7.82, "d2": 5.14, "allWr": 45, "defaultLane": "top"}, {"cid": 876, "vsWr": 52.81, "n": 1350, "d1": 5.62, "d2": 2.93, "allWr": 47.19, "defaultLane": "jungle"}, {"cid": 141, "vsWr": 52.65, "n": 1814, "d1": 4.07, "d2": 1.38, "allWr": 48.58, "defaultLane": "jungle"}, {"cid": 234, "vsWr": 52.6, "n": 7649, "d1": 2.81, "d2": 0.12, "allWr": 49.79, "defaultLane": "jungle"}, {"cid": 24, "vsWr": 52.55, "n": 923, "d1": 4.56, "d2": 1.87, "allWr": 47.99, "defaultLane": "top"}, {"cid": 36, "vsWr": 52.32, "n": 1705, "d1": 3.78, "d2": 1.09, "allWr": 48.54, "defaultLane": "top"}, {"cid": 104, "vsWr": 52.21, "n": 2400, "d1": 3.71, "d2": 1.02, "allWr": 48.5, "defaultLane": "jungle"}, {"cid": 59, "vsWr": 52.17, "n": 4108, "d1": 3.88, "d2": 1.19, "allWr": 48.29, "defaultLane": "jungle"}, {"cid": 904, "vsWr": 52.12, "n": 683, "d1": 3.71, "d2": 1.02, "allWr": 48.41, "defaultLane": "top"}, {"cid": 56, "vsWr": 51.95, "n": 1434, "d1": 3.71, "d2": 1.02, "allWr": 48.24, "defaultLane": "jungle"}, {"cid": 72, "vsWr": 51.82, "n": 411, "d1": 3.92, "d2": 1.23, "allWr": 47.9, "defaultLane": "jungle"}, {"cid": 266, "vsWr": 51.79, "n": 865, "d1": 2.81, "d2": 0.12, "allWr": 48.98, "defaultLane": "top"}, {"cid": 233, "vsWr": 51.6, "n": 1093, "d1": 3.63, "d2": 0.94, "allWr": 47.97, "defaultLane": "jungle"}, {"cid": 254, "vsWr": 51.55, "n": 2382, "d1": 2.01, "d2": -0.68, "allWr": 49.54, "defaultLane": "jungle"}, {"cid": 113, "vsWr": 51.47, "n": 645, "d1": 2.84, "d2": 0.15, "allWr": 48.63, "defaultLane": "jungle"}, {"cid": 25, "vsWr": 51.41, "n": 142, "d1": 5.5, "d2": 2.81, "allWr": 45.91, "defaultLane": "support"}, {"cid": 64, "vsWr": 51.37, "n": 7639, "d1": 3.76, "d2": 1.07, "allWr": 47.61, "defaultLane": "jungle"}, {"cid": 126, "vsWr": 51.2, "n": 5977, "d1": 1.36, "d2": -1.33, "allWr": 49.84, "defaultLane": "jungle"}, {"cid": 517, "vsWr": 51.16, "n": 2541, "d1": 2.61, "d2": -0.08, "allWr": 48.55, "defaultLane": "middle"}, {"cid": 60, "vsWr": 51.02, "n": 1468, "d1": 3.88, "d2": 1.19, "allWr": 47.14, "defaultLane": "jungle"}, {"cid": 5, "vsWr": 51, "n": 1994, "d1": 2.62, "d2": -0.07, "allWr": 48.38, "defaultLane": "jungle"}, {"cid": 62, "vsWr": 50.69, "n": 1310, "d1": 2.13, "d2": -0.56, "allWr": 48.56, "defaultLane": "jungle"}, {"cid": 143, "vsWr": 50.56, "n": 807, "d1": 4.49, "d2": 1.8, "allWr": 46.07, "defaultLane": "support"}, {"cid": 30, "vsWr": 50.41, "n": 1335, "d1": 2.51, "d2": -0.18, "allWr": 47.9, "defaultLane": "jungle"}, {"cid": 79, "vsWr": 50.29, "n": 344, "d1": 2.96, "d2": 0.27, "allWr": 47.33, "defaultLane": "top"}, {"cid": 91, "vsWr": 50.09, "n": 2847, "d1": 1.92, "d2": -0.77, "allWr": 48.17, "defaultLane": "jungle"}, {"cid": 35, "vsWr": 50.07, "n": 2027, "d1": 3.89, "d2": 1.2, "allWr": 46.18, "defaultLane": "jungle"}, {"cid": 120, "vsWr": 49.94, "n": 2549, "d1": 1.06, "d2": -1.63, "allWr": 48.88, "defaultLane": "jungle"}, {"cid": 245, "vsWr": 49.9, "n": 5405, "d1": 2.87, "d2": 0.18, "allWr": 47.03, "defaultLane": "jungle"}, {"cid": 107, "vsWr": 49.86, "n": 2417, "d1": 2.87, "d2": 0.18, "allWr": 46.99, "defaultLane": "jungle"}, {"cid": 131, "vsWr": 49.81, "n": 5130, "d1": 3.1, "d2": 0.41, "allWr": 46.71, "defaultLane": "jungle"}, {"cid": 80, "vsWr": 49.78, "n": 448, "d1": 1.38, "d2": -1.31, "allWr": 48.4, "defaultLane": "support"}, {"cid": 106, "vsWr": 49.77, "n": 1736, "d1": 3.74, "d2": 1.05, "allWr": 46.03, "defaultLane": "jungle"}, {"cid": 950, "vsWr": 49.75, "n": 1379, "d1": 0.9, "d2": -1.79, "allWr": 48.85, "defaultLane": "middle"}, {"cid": 11, "vsWr": 49.66, "n": 1921, "d1": 2.48, "d2": -0.21, "allWr": 47.18, "defaultLane": "jungle"}, {"cid": 246, "vsWr": 49.4, "n": 2417, "d1": -0.34, "d2": -3.03, "allWr": 49.74, "defaultLane": "jungle"}, {"cid": 238, "vsWr": 49.27, "n": 3292, "d1": 1.66, "d2": -1.03, "allWr": 47.61, "defaultLane": "middle"}, {"cid": 28, "vsWr": 49.21, "n": 1325, "d1": 2.85, "d2": 0.16, "allWr": 46.36, "defaultLane": "jungle"}, {"cid": 76, "vsWr": 49.2, "n": 1817, "d1": 2.04, "d2": -0.65, "allWr": 47.16, "defaultLane": "jungle"}, {"cid": 163, "vsWr": 49.17, "n": 1208, "d1": 0.83, "d2": -1.86, "allWr": 48.34, "defaultLane": "middle"}, {"cid": 20, "vsWr": 49.06, "n": 2242, "d1": 3.14, "d2": 0.45, "allWr": 45.92, "defaultLane": "jungle"}, {"cid": 887, "vsWr": 48.77, "n": 2487, "d1": 2.75, "d2": 0.06, "allWr": 46.02, "defaultLane": "jungle"}, {"cid": 154, "vsWr": 48.42, "n": 2210, "d1": 2.31, "d2": -0.38, "allWr": 46.11, "defaultLane": "jungle"}, {"cid": 200, "vsWr": 48.34, "n": 1022, "d1": 1.86, "d2": -0.83, "allWr": 46.48, "defaultLane": "jungle"}, {"cid": 121, "vsWr": 48.26, "n": 5582, "d1": 1.63, "d2": -1.06, "allWr": 46.63, "defaultLane": "jungle"}, {"cid": 421, "vsWr": 47.74, "n": 2298, "d1": 2.66, "d2": -0.02, "allWr": 45.08, "defaultLane": "jungle"}, {"cid": 203, "vsWr": 47.38, "n": 1258, "d1": 0.67, "d2": -2.02, "allWr": 46.71, "defaultLane": "jungle"}, {"cid": 427, "vsWr": 46.85, "n": 1157, "d1": 1.11, "d2": -1.58, "allWr": 45.74, "defaultLane": "jungle"}, {"cid": 9, "vsWr": 46.39, "n": 1233, "d1": 0.8, "d2": -1.89, "allWr": 45.59, "defaultLane": "jungle"}, {"cid": 78, "vsWr": 46.27, "n": 201, "d1": -2.59, "d2": -5.28, "allWr": 48.86, "defaultLane": "support"}, {"cid": 31, "vsWr": 46.22, "n": 251, "d1": -0.24, "d2": -2.93, "allWr": 46.46, "defaultLane": "top"}], "response": {"valid": true, "duration": "56"}}